BCD.v
module BCD (clk, rst_syn, load_syn, Din);
input clk;
input rst_syn;
input load_syn;
input [3:0] Din;
output [3:0] Q_out;
reg [3:0] Q_out;
output [7:0] Ans;
reg [7:0] Ans;
initial
begin
    Q_out[3:0]=4'b0000;
end

always@ (posedge clk)
begin
    if (!rst_syn)
        Q_out=4'b0000;
    else if (load_syn)
        Q_out=Din;
    else if (Q_out == 9)
        Q_out=0;
    else
        Q_out=Q_out+1;
end

always @(Q_out)
case (Q_out)
    4'b0000:
        Ans=8'b11000000;
    4'b0001:
        Ans=8'b11111001;
    4'b0010:
        Ans=8'b10100100;
    4'b0011:
        Ans=8'b10110000;
    4'b0100:
        Ans=8'b10011001;
    4'b0101:
        Ans=8'b10010010;
    4'b0110:
        Ans=8'b10000010;
    4'b0111:
        Ans=8'b11111000;
    4'b1000:
        Ans=8'b10000000;
    4'b1001:
        Ans=8'b10010000;
    default:
        Ans=8'b10000100;
endcase

endmodule

TestBench.v
module BCDtoSEVEN_tb();
reg clk_tb, reset_tb, load_tb;
reg [3:0] Din_tb;
BCD BCD_1(.clk(clk_tb), .rst_syn(reset_tb), .load_syn(load_tb), .Din(Din_tb));

initial
begin
    clk_tb=1'b1;
    reset_tb=1'b1;
    load_tb=1'b0;
    Din_tb=4'b0101;
end

always
begin
    #10 clk_tb = ~clk_tb;
end

initial
begin
    #80 clk_tb = 1'b0;
    #10 clk_tb = 1'b1;
end

initial
begin
    #80 clk_tb = 1'b1;
    #10 clk_tb = 1'b0;
end

initial
begin
    #120 clk_tb = 1'b1;
    #10 clk_tb = 1'b0;
end

initial
begin
    #400 $finish;
end

initial
begin
    $dumpfile("0506.vcd");
    $dumpvars(0, BCD_1);
end
endmodule

0506.vcd
$date
	Thu May 05 17:56:15 2022
$end
$version
	Icarus Verilog
$end
$timescale
	1s
$end
$scope module BCDtoSEVEN_tb $end
$scope module BCD_1 $end
$var wire 4 ! Din [3:0] $end
$var wire 1 " clk $end
$var wire 1 # load_syn $end
$var wire 1 $ rst_syn $end
$var reg 8 % Ans [7:0] $end
$var reg 4 & Q_out [3:0] $end
$upscope $end
$upscope $end
$enddefinitions $end
#0
$dumpvars
b1 &
b11111001 %
1$
0#
1"
b101 !
$end
#10
0"
#20
b10100100 %
b10 &
1"
#30
0"
#40
b10110000 %
b11 &
1"
#50
0"
#60
b10011001 %
b100 &
1"
#70
0"
#80
b10010010 %
b101 &
0"
#90
b10000010 %
b110 &
1"
#100
0"
#110
b11111000 %
b111 &
1"
#120
0"
#130
b10000000 %
b1000 &
1"
#140
0"
#150
b10010000 %
b1001 &
1"
#160
0"
#170
b11000000 %
b0 &
1"
#180
0"
#190
b11111001 %
b1 &
1"
#200
0"
#210
b10100100 %
b10 &
1"
#220
0"
#230
b10110000 %
b11 &
1"
#240
0"
#250
b10011001 %
b100 &
1"
#260
0"
#270
b10010010 %
b101 &
1"
#280
0"
#290
b10000010 %
b110 &
1"
#300
0"
#310
b11111000 %
b111 &
1"
#320
0"
#330
b10000000 %
b1000 &
1"
#340
0"
#350
b10010000 %
b1001 &
1"
#360
0"
#370
b11000000 %
b0 &
1"
#380
0"
#390
b11111001 %
b1 &
1"
